{
  "tags": [
    {
      "name": "release",
      "version": "3.2.1",
      "commit": "b29ecef",
      "upstream": "Releases",
      "lastUpdated": "2021-04-15T13:44:43.333Z"
    },
    {
      "name": "testing",
      "version": "3.3.0RC1",
      "commit": "48bcce8",
      "upstream": "Pre-releases",
      "lastUpdated": "2021-05-13T17:12:20.901Z"
    },
    {
      "name": "nightly",
      "version": "745459e69f92ca780105a01c755620a114576e84",
      "commit": "f8db8f5",
      "upstream": "Every commit to develop",
      "lastUpdated": "2021-05-13T13:44:35.536Z"
    }
  ],
  "pulls": 2339632,
  "stars": 3
}
