{
  "tags": [
    {
      "name": "release",
      "version": "3.2.1",
      "commit": "b29ecef",
      "upstream": "Releases",
      "lastUpdated": "2021-04-15T13:44:43.333Z"
    },
    {
      "name": "testing",
      "version": "3.3.0Beta3",
      "commit": "e203a60",
      "upstream": "Pre-releases",
      "lastUpdated": "2021-04-29T09:47:43.214Z"
    },
    {
      "name": "nightly",
      "version": "b0eaf93331f13653ea8da038cbd7761782e99401",
      "commit": "8fcda52",
      "upstream": "Every commit to develop",
      "lastUpdated": "2021-05-01T10:46:52.359Z"
    }
  ],
  "pulls": 2328808,
  "stars": 3
}
