{
  "tags": [
    {
      "name": "release",
      "version": "3.2.0",
      "commit": "5fd3905",
      "upstream": "Releases",
      "lastUpdated": "2021-03-09T19:39:30.456Z"
    },
    {
      "name": "testing",
      "version": "3.2.0",
      "commit": "2faac60",
      "upstream": "Pre-releases",
      "lastUpdated": "2021-03-09T19:40:03.769Z"
    },
    {
      "name": "nightly",
      "version": "a86273f213d4ddff0b593f6bb3af90e987ac9c3d",
      "commit": "b64bea9",
      "upstream": "Every commit to develop",
      "lastUpdated": "2021-03-14T11:34:11.926Z"
    }
  ],
  "pulls": 2263854,
  "stars": 3
}
